haversine/__init__.py
haversine/haversine.py
haversine-2.5.0.dist-info/LICENSE
haversine-2.5.0.dist-info/METADATA
haversine-2.5.0.dist-info/WHEEL
haversine-2.5.0.dist-info/top_level.txt
haversine-2.5.0.dist-info/RECORD
