Metadata-Version: 2.1
Name: haversine
Version: 2.5.0
Summary: Calculate the distance between 2 points on Earth.
Home-page: https://github.com/mapado/haversine
Author: Balthazar Rouberol
Maintainer: Julien Deniau
Maintainer-email: julien.deniau@mapado.com
License: MIT
Platform: UNKNOWN
Classifier: Development Status :: 4 - Beta
Classifier: Intended Audience :: Developers
Classifier: License :: OSI Approved :: MIT License
Classifier: Programming Language :: Python
Classifier: Programming Language :: Python :: 3.5
Classifier: Programming Language :: Python :: 3.6
Classifier: Programming Language :: Python :: 3.7
Classifier: Programming Language :: Python :: 3.8
Classifier: Programming Language :: Python :: 3.9
Classifier: Topic :: Scientific/Engineering :: Mathematics
Requires-Python: >=3.5
License-File: LICENSE
